betterocr/__init__.py
betterocr/detect.py
betterocr/engines/easy_pororo_ocr/__init__.py
betterocr/engines/easy_pororo_ocr/pororo/__init__.py
betterocr/engines/easy_pororo_ocr/pororo/models/brainOCR/__init__.py
betterocr/engines/easy_pororo_ocr/pororo/models/brainOCR/_dataset.py
betterocr/engines/easy_pororo_ocr/pororo/models/brainOCR/_modules.py
betterocr/engines/easy_pororo_ocr/pororo/models/brainOCR/brainocr.py
betterocr/engines/easy_pororo_ocr/pororo/models/brainOCR/craft.py
betterocr/engines/easy_pororo_ocr/pororo/models/brainOCR/craft_utils.py
betterocr/engines/easy_pororo_ocr/pororo/models/brainOCR/detection.py
betterocr/engines/easy_pororo_ocr/pororo/models/brainOCR/imgproc.py
betterocr/engines/easy_pororo_ocr/pororo/models/brainOCR/model.py
betterocr/engines/easy_pororo_ocr/pororo/models/brainOCR/modules/__init__.py
betterocr/engines/easy_pororo_ocr/pororo/models/brainOCR/modules/basenet.py
betterocr/engines/easy_pororo_ocr/pororo/models/brainOCR/modules/feature_extraction.py
betterocr/engines/easy_pororo_ocr/pororo/models/brainOCR/modules/prediction.py
betterocr/engines/easy_pororo_ocr/pororo/models/brainOCR/modules/sequence_modeling.py
betterocr/engines/easy_pororo_ocr/pororo/models/brainOCR/modules/transformation.py
betterocr/engines/easy_pororo_ocr/pororo/models/brainOCR/recognition.py
betterocr/engines/easy_pororo_ocr/pororo/models/brainOCR/utils.py
betterocr/engines/easy_pororo_ocr/pororo/pororo.py
betterocr/engines/easy_pororo_ocr/pororo/tasks/__init__.py
betterocr/engines/easy_pororo_ocr/pororo/tasks/optical_character_recognition.py
betterocr/engines/easy_pororo_ocr/pororo/tasks/utils/__init__.py
betterocr/engines/easy_pororo_ocr/pororo/tasks/utils/base.py
betterocr/engines/easy_pororo_ocr/pororo/tasks/utils/config.py
betterocr/engines/easy_pororo_ocr/pororo/tasks/utils/download_utils.py
betterocr/engines/easy_pororo_ocr/pororo/utils.py
betterocr/engines/easy_pororo_ocr/utils/__init__.py
betterocr/engines/easy_pororo_ocr/utils/image_convert.py
betterocr-1.2.0.dist-info/LICENSE
betterocr-1.2.0.dist-info/METADATA
betterocr-1.2.0.dist-info/WHEEL
betterocr-1.2.0.dist-info/RECORD
