Metadata-Version: 2.1
Name: betterocr
Version: 1.2.0
Summary: Better text detection by combining OCR engines with LLM.
Author: Junho Yeo
Author-email: i@junho.io
Requires-Python: >=3.11,<3.13
Classifier: Programming Language :: Python :: 3
Classifier: Programming Language :: Python :: 3.11
Requires-Dist: easyocr (>=1.7.1,<2.0.0)
Requires-Dist: numpy (>=1.26.1,<2.0.0)
Requires-Dist: openai (>=1.0.0b3,<2.0.0)
Requires-Dist: opencv-python (>=4.8.1.78,<5.0.0.0)
Requires-Dist: pandas (>=2.1.2,<3.0.0)
Requires-Dist: pytesseract (>=0.3.10,<0.4.0)
